askit/__init__.py
askit/config.json
askit/main.py
askit-0.1.45.dist-info/entry_points.txt
askit-0.1.45.dist-info/WHEEL
askit-0.1.45.dist-info/METADATA
askit-0.1.45.dist-info/RECORD
