Metadata-Version: 2.1
Name: askit
Version: 0.1.45
Summary: Ask OpenAI your question right inside your terminal
Author: Phil Harper
Author-email: phil@imrge.co
Requires-Python: >=3.10,<4.0
Classifier: Programming Language :: Python :: 3
Classifier: Programming Language :: Python :: 3.10
Classifier: Programming Language :: Python :: 3.11
Requires-Dist: openai (>=0.25.0,<0.26.0)
Requires-Dist: typer[all] (>=0.6.1,<0.7.0)
